globalnoc/wsc/__init__.py
globalnoc/wsc/__main__.py
globalnoc_wsc-1.0.2.dist-info/LICENSE
globalnoc_wsc-1.0.2.dist-info/METADATA
globalnoc_wsc-1.0.2.dist-info/WHEEL
globalnoc_wsc-1.0.2.dist-info/entry_points.txt
globalnoc_wsc-1.0.2.dist-info/RECORD
