Metadata-Version: 2.1
Name: globalnoc-wsc
Version: 1.0.2
Summary: GlobalNOC Web Service Client with SAML2 and basic auth support
License: Apache-2.0
Author: GlobalNOC SysEng
Author-email: syseng@globalnoc.iu.edu
Requires-Python: >=3.8.11,<4.0.0
Classifier: License :: OSI Approved :: Apache Software License
Classifier: Programming Language :: Python :: 3
Classifier: Programming Language :: Python :: 3.9
Classifier: Programming Language :: Python :: 3.10
Classifier: Programming Language :: Python :: 3.11
Requires-Dist: lxml (>=4.9.2,<5.0.0)
Requires-Dist: requests (>=2.28.2,<3.0.0)
Requires-Dist: urllib3 (<2.0.0) ; python_version < "3.10"
Requires-Dist: urllib3 (>=2.0.2,<3.0.0) ; python_version >= "3.10"
